omeka_s_gateway/__init__.py
omeka_s_gateway-0.0.10.dist-info/METADATA
omeka_s_gateway-0.0.10.dist-info/WHEEL
omeka_s_gateway-0.0.10.dist-info/top_level.txt
omeka_s_gateway-0.0.10.dist-info/RECORD
